README.rst
setup.py
./Constants.py
./Map.py
./Tileset.py
./__init__.py
TileEngine.egg-info/PKG-INFO
TileEngine.egg-info/SOURCES.txt
TileEngine.egg-info/dependency_links.txt
TileEngine.egg-info/requires.txt
TileEngine.egg-info/top_level.txt
test/test_Map.py
test/test_Tileset.py