Metadata-Version: 1.1
Name: TileEngine
Version: 1.0.0
Summary: Basic 2D tile-based game engine, based on Pokemon.
Home-page: https://github.com/WORD559/TileEngine
Author: WORD559
Author-email: josh.barrass.work@gmail.com
License: UNKNOWN
Keywords: game engine tile pokemon
Platform: UNKNOWN
Classifier: Intended Audience :: Developers
Classifier: Natural Language :: English
Classifier: Programming Language :: Python :: 3
